{
    "contacts": {
        "main": {
            "name": "Lucas Sinclair",
            "email": "lucas.sinclair@ebc.uu.se"
        },
        "pi": {
            "name": "Alexander Eiler",
            "email": "alexander.eiler@ebc.uu.se"
        }
    },

    "run_num":       -1,
    "sample_num":    1,
    "project":       "454",
    "project_name":  "454 sequencing",
    "sample":        "soil_454",
    "sample_name":   "454 sequencing of the soil sample",
    "group":         "pyro",

    "files": [
        {"path": "/proj/b2011032/INBOX/D_2012_06_16_01_28_05_tank_signalProcessingAmplicons/sff/HPQTMO402.sff",
            "mid": "TCAGAGA", "midnum": 66}
    ],

    "predenoised": null
}